comdirect_client/__init__.py
comdirect_client/client.py
comdirect_client/exceptions.py
comdirect_client/models.py
comdirect_client/token_storage.py
comdirect_client-0.1.0.dist-info/METADATA
comdirect_client-0.1.0.dist-info/WHEEL
comdirect_client-0.1.0.dist-info/licenses/LICENSE
comdirect_client-0.1.0.dist-info/RECORD
