Metadata-Version: 2.4
Name: comdirect-client
Version: 0.1.0
Summary: Async Python client library for Comdirect Banking API with automatic token refresh
License: MIT
License-File: LICENSE
Keywords: comdirect,banking,api,async,oauth2
Author: Philipp
Requires-Python: >=3.9,<4.0
Classifier: Development Status :: 4 - Beta
Classifier: Intended Audience :: Developers
Classifier: License :: OSI Approved :: MIT License
Classifier: Operating System :: OS Independent
Classifier: Programming Language :: Python :: 3
Classifier: Programming Language :: Python :: 3.9
Classifier: Programming Language :: Python :: 3.10
Classifier: Programming Language :: Python :: 3.11
Classifier: Programming Language :: Python :: 3.12
Classifier: Programming Language :: Python :: 3.13
Classifier: Programming Language :: Python :: 3.14
Classifier: Topic :: Office/Business :: Financial
Classifier: Topic :: Software Development :: Libraries :: Python Modules
Requires-Dist: httpx (>=0.27.0,<0.28.0)
Requires-Dist: pydantic (>=2.0.0,<3.0.0)
Project-URL: Documentation, https://github.com/mcdax/comdirect-python-library#readme
Project-URL: Homepage, https://github.com/mcdax/comdirect-python-library
Project-URL: Repository, https://github.com/mcdax/comdirect-python-library
